bsp/__init__.py
bsp/bsp.py
bsp/json.py
bsp-1.0.1.dist-info/LICENSE
bsp-1.0.1.dist-info/METADATA
bsp-1.0.1.dist-info/WHEEL
bsp-1.0.1.dist-info/top_level.txt
bsp-1.0.1.dist-info/RECORD
