Metadata-Version: 2.1
Name: bsp
Version: 1.0.1
Summary: Basic Socket Protocol
Home-page: https://github.com/hyurl/bsp-py
Author: Ayon Lee
Author-email: i@hyurl.com
License: UNKNOWN
Platform: UNKNOWN
Classifier: Programming Language :: Python :: 3
Classifier: License :: OSI Approved :: MIT License
Classifier: Operating System :: OS Independent
Requires-Python: >=3.6
